lyric_task/__init__.py
lyric_task/log.py
lyric_task/pickle.py
lyric_task/std.py
lyric_task/utils.py
lyric_task-0.1.7.dist-info/METADATA
lyric_task-0.1.7.dist-info/WHEEL
lyric_task-0.1.7.dist-info/RECORD
