Metadata-Version: 2.3
Name: lyric-task
Version: 0.1.7
Summary: Add your description here
Author-email: Fangyin Cheng <staneyffer@gmail.com>
Requires-Python: >=3.8
Requires-Dist: cloudpickle
Requires-Dist: msgpack
